dhlab-2.42.1.dist-info/METADATA
dhlab-2.42.1.dist-info/WHEEL
dhlab-2.42.1.dist-info/entry_points.txt
dhlab-2.42.1.dist-info/licenses/LICENSE
dhlab/__init__.py
dhlab/__init__.pyi
dhlab/api/__init__.py
dhlab/api/dhlab_api.py
dhlab/api/nb_ngram_api.py
dhlab/api/nb_search_api.py
dhlab/api/utils.py
dhlab/constants.py
dhlab/css_style_sheets/grade3.css
dhlab/css_style_sheets/monokai.css
dhlab/css_style_sheets/nb_notebook.css
dhlab/css_style_sheets/nb_notebook_2.css
dhlab/css_style_sheets/nb_notebook_blue.css
dhlab/future/__init__.py
dhlab/future/corpus_conc_coll.py
dhlab/future/ngram.py
dhlab/images/__init__.py
dhlab/images/nbpictures.py
dhlab/legacy/__init__.py
dhlab/legacy/graph_networkx_louvain.py
dhlab/legacy/module_update.py
dhlab/legacy/nb_external_files.py
dhlab/legacy/nbpictures.py
dhlab/legacy/nbtext.py
dhlab/legacy/token_map.py
dhlab/ngram/__init__.py
dhlab/ngram/__init__.pyi
dhlab/ngram/nb_ngram.py
dhlab/ngram/ngram.py
dhlab/text/__init__.py
dhlab/text/__init__.pyi
dhlab/text/chunking.py
dhlab/text/conc_coll.py
dhlab/text/corpus.py
dhlab/text/corpus_collection.py
dhlab/text/dhlab_object.py
dhlab/text/dispersion.py
dhlab/text/geo_data.py
dhlab/text/nb_search_text.py
dhlab/text/parse.py
dhlab/text/utils.py
dhlab/text/wildcard.py
dhlab/trigram_lang_model/nno_trilangmodel.json
dhlab/trigram_lang_model/nob_trilangmodel.json
dhlab/utils/__init__.py
dhlab/utils/display.py
dhlab/utils/files.py
dhlab/visualize/__init__.py
dhlab/visualize/cloud.py
dhlab/visualize/df.py
dhlab/wordbank/__init__.py
dhlab/wordbank/__init__.pyi
dhlab/wordbank/wordbank.py
dhlab-2.42.1.dist-info/RECORD
