Metadata-Version: 2.1
Name: dhlab
Version: 2.42.1
Summary: Text and image analysis of the digital collection (books, newspapers, periodicals, and images) at the National Library of Norway
Author-Email: "The Digital Humanities Lab at The National Library of Norway (NB)" <dh-lab@nb.no>
License: MIT
Classifier: Programming Language :: Python :: 3
Classifier: License :: OSI Approved :: MIT License
Classifier: Operating System :: OS Independent
Project-URL: Bug Tracker, https://github.com/NationalLibraryOfNorway/DHLAB/issues
Project-URL: homepage, https://www.nb.no/dh-lab/
Project-URL: repository, https://github.com/NationalLibraryOfNorway/DHLAB
Project-URL: documentation, https://nationallibraryofnorway.github.io/DHLAB/
Requires-Python: <4.0,>=3.10
Requires-Dist: ipython
Requires-Dist: matplotlib
Requires-Dist: networkx
Requires-Dist: pandas
Requires-Dist: python-louvain
Requires-Dist: requests
Requires-Dist: seaborn
Requires-Dist: openpyxl
Requires-Dist: beautifulsoup4
Requires-Dist: jinja2
Requires-Dist: tqdm
Requires-Dist: nb-tokenizer
Requires-Dist: lazy-loader
Requires-Dist: wordcloud
Requires-Dist: scipy
